datacollectors/__init__.py
datacollectors/datacollector_Barchart.py
datacollectors/datacollector_Boliga.py
datacollectors/datacollector_Business_insider.py
datacollectors/datacollector_ECB.py
datacollectors/datacollector_Entsoe.py
datacollectors/datacollector_ICE.py
datacollectors/datacollector_energidataservice.py
datacollectors/parms_ICE/__init__.py
datacollectors/parms_ICE/commodities.csv
datacollectors/parms_barchart/__init__.py
datacollectors/parms_barchart/commodity_codes.csv
datacollectors/parms_barchart/month_codes.csv
datacollectors/parms_business_insider/__init__.py
datacollectors/parms_business_insider/metal_codes.csv
datacollectors/parms_entsoe/A44.csv
datacollectors/parms_entsoe/A65.csv
datacollectors/parms_entsoe/A73.csv
datacollectors/parms_entsoe/A75.csv
datacollectors/parms_entsoe/__init__.py
datacollectors/parms_entsoe/entsoe_table_parms.csv
datacollectors/parms_entsoe/psr_types.csv
datacollectors-0.7.35.dist-info/licenses/LICENCE.txt
datacollectors-0.7.35.dist-info/METADATA
datacollectors-0.7.35.dist-info/WHEEL
datacollectors-0.7.35.dist-info/top_level.txt
datacollectors-0.7.35.dist-info/RECORD
